README.txt
setup.cfg
setup.py
collective/__init__.py
collective.contentMapper.egg-info/PKG-INFO
collective.contentMapper.egg-info/SOURCES.txt
collective.contentMapper.egg-info/dependency_links.txt
collective.contentMapper.egg-info/entry_points.txt
collective.contentMapper.egg-info/namespace_packages.txt
collective.contentMapper.egg-info/not-zip-safe
collective.contentMapper.egg-info/paster_plugins.txt
collective.contentMapper.egg-info/requires.txt
collective.contentMapper.egg-info/top_level.txt
collective/contentMapper/__init__.py
collective/contentMapper/categoryutils.py
collective/contentMapper/config.py
collective/contentMapper/configure.zcml
collective/contentMapper/events.py
collective/contentMapper/interfaces.py
collective/contentMapper/tests.py
collective/contentMapper/browser/__init__.py
collective/contentMapper/browser/configure.zcml
collective/contentMapper/browser/images/BigMarker.png
collective/contentMapper/browser/images/MediumMarker.png
collective/contentMapper/browser/images/NoordHollandMap.png
collective/contentMapper/browser/images/SmallMarker.png
collective/contentMapper/browser/stylesheets/mapNavigator.css
collective/contentMapper/portlets/__init__.py
collective/contentMapper/portlets/configure.zcml
collective/contentMapper/portlets/mapNavigator.pt
collective/contentMapper/portlets/selector.py
collective/contentMapper/profiles/default/cssregistry.xml
collective/contentMapper/profiles/default/metadata.xml
collective/contentMapper/profiles/default/portlets.xml
collective/contentMapper/profiles/default/registry.xml
docs/HISTORY.txt
docs/INSTALL.txt
docs/LICENSE.GPL
docs/LICENSE.txt