Metadata-Version: 1.0
Name: collective.contentMapper
Version: 0.6
Summary: Overrides collective.tagNavigator and adds a map interface instead of the menu
Home-page: http://svn.plone.org/svn/collective/
Author: David Jonas
Author-email: david@intk.com
License: GPL
Keywords: tags navigation portlet maps
Platform: UNKNOWN
Classifier: Framework :: Plone
Classifier: Programming Language :: Python
